{
  "name": "Alcose",
  "slug": "alcose",
  "category": "credit-unions",
  "subcategories": [
    "credit-union",
    "fdic-equivalent"
  ],
  "description_short": "Alcose Credit Union is a member-owned financial institution serving Allegheny County School Employees and affiliated groups since 1950, offering checking, savings, loans, and credit cards.",
  "description_long": "Alcose Credit Union was established on February 25, 1950, as a credit union specifically serving Allegheny County School Employees (the source of the 'Alcose' acronym). Over the decades, the credit union has expanded its membership eligibility through mergers with additional agencies and companies. The organization operates on the traditional credit union philosophy of 'People Helping People,' positioning itself as a member-focused financial institution designed to serve community needs.\n\nAlcose offers a comprehensive suite of consumer financial products including auto loans, signature loans, Visa credit cards, checking and savings accounts, and debit cards. Members can access services through online banking, a mobile app with remote check deposit capabilities, and multiple physical branch locations. The credit union also provides specialized services such as Early Payday (allowing paycheck access up to two days earlier for a $25 fee), PayM\u014dli mobile payment transfers, shared branching through the CO-OP network, and overdraft protection on share draft accounts. Their current rates include auto loans starting at 4.50% APR, signature loans at 9.25% APR, and Visa credit cards at 8.90% APR with no annual fee.\n\nAlcose distinguishes itself through membership restrictions tied to specific employer groups and their legacy as a 75-year-old community institution. The credit union emphasizes member benefits like the Early Payday service and credit life insurance options on credit cards. Their integration with the CO-OP shared branching network provides access to a broader network of ATMs and branches beyond their primary locations. The organization actively promotes fraud prevention tools including transaction alerts, card freeze options, and real-time monitoring capabilities.\n\nAlcose is a legitimate, federally-insured credit union appropriate for members who qualify for their eligibility requirements and seek traditional banking services with a community-oriented approach. Primary limitations include membership restrictions based on employer affiliation, relatively limited service offerings compared to large national banks, and the Early Payday fee structure ($25 per use) which may not appeal to frequent users of this service.",
  "logo_url": "",
  "website_url": "https://www.alcosecu.com",
  "affiliate_url": "",
  "affiliate_program": "",
  "pricing": {
    "monthly_price": 0,
    "setup_fee": 0,
    "money_back_guarantee": false,
    "guarantee_details": "",
    "free_consultation": true,
    "tiers": [],
    "currency": "USD"
  },
  "services": [
    "Auto loans (4.50% APR minimum)",
    "Signature loans (9.25% APR minimum)",
    "Visa credit cards (8.90% APR, no annual fee)",
    "Checking and savings accounts with VISA debit cards",
    "Early Payday service ($25 fee per use)",
    "PayM\u014dli mobile money transfer service",
    "Mobile banking app with remote check deposit",
    "Online banking portal",
    "CO-OP shared branching network access",
    "ATM access through shared networks",
    "Overdraft protection on share draft accounts",
    "Credit life insurance on credit cards"
  ],
  "pros": [
    "No annual fee on Visa credit cards with 25-day grace period",
    "Early Payday service allows access to paycheck up to two days earlier",
    "Access to 75-year track record and federally-insured deposits as a credit union",
    "Mobile app with remote check deposit and card freeze capabilities",
    "Credit life insurance coverage available on credit cards at low cost",
    "CO-OP shared branching network provides expanded branch and ATM access",
    "Competitive auto loan rates starting at 4.50% APR"
  ],
  "cons": [
    "Membership restricted to Allegheny County School Employees and affiliated groups only",
    "Early Payday service charges $25 per use, making frequent use expensive",
    "Limited mention of savings account interest rates or CD rates on website",
    "No indication of automatic overdraft protection without member opt-in",
    "Signature loan APR of 9.25% is higher than competitive personal loan market rates"
  ],
  "contact": {
    "phone": "",
    "address": ",  "
  },
  "bbb_rating": "",
  "founded_year": 1950,
  "headquarters": ", ",
  "states_served": [],
  "data_source": "enriched",
  "ncua_charter": "61926",
  "published": true,
  "review_status": "draft",
  "features": {
    "credit_monitoring": false,
    "all_three_bureaus": false,
    "goodwill_letters": false,
    "cease_desist_letters": false,
    "debt_validation": false,
    "credit_education": true,
    "identity_theft_protection": false,
    "score_tracking": false,
    "mobile_app": false,
    "online_portal": true,
    "personal_advisor": true,
    "ai_powered": false
  },
  "company_info": {
    "founded_year": 1950,
    "headquarters": ", ",
    "city": "",
    "state": "",
    "employees": "",
    "bbb_rating": "",
    "bbb_accredited": false,
    "certifications": [
      "NCUA Insured",
      "Charter #61926"
    ]
  },
  "rating": 4.0,
  "rating_breakdown": {
    "value": 5.0,
    "effectiveness": 3.5,
    "customer_service": 3.7,
    "transparency": 4.2,
    "ease_of_use": 4.0
  },
  "best_for": [
    "Allegheny County School Employees and their family members",
    "Members of eligible companies and agencies who merged into Alcose",
    "Consumers seeking no-fee credit card options with credit life insurance",
    "Individuals who want early paycheck access for planned cash needs"
  ],
  "similar_lenders": [],
  "diagnosis": "Alcose is best for eligible members of Allegheny County School Employees and affiliated groups seeking traditional banking services with a community-oriented credit union structure. The main caveat is strict membership eligibility requirements\u2014you cannot join unless you work for or are affiliated with specific employers, making this institution inaccessible to the general public.",
  "typical_results_timeline": "Membership approval and account opening typically takes 1-3 business days. Loan decisions are usually faster than traditional banks.",
  "last_updated": "2026-03-21",
  "cities_served": [],
  "phone": "4126732450",
  "address": ",  ",
  "processing_status": "ready_for_index",
  "quality_score": 11,
  "enrichment_attempts": 1,
  "no_index": false,
  "ncua_charter_number": "61926",
  "ncua_official_name": "ALCOSE",
  "ncua_match_score": 1.0,
  "ncua_resolved_at": "2026-04-14T13:18:49.163255Z",
  "city": "White Oak",
  "state": "PA",
  "website": "https://www.alcosecu.com",
  "meta_title": "Alcose \u2014 Credit Union in White Oak, PA | CreditDoc",
  "meta_description": "Alcose \u2014 NCUA-insured credit union in White Oak, PA. Member-owned, not-for-profit. Loans, savings, and member services.",
  "has_been_enriched": true,
  "qc_passed_at": "2026-04-14",
  "last_engine_run": "2026-04-15"
}