{
  "name": "Cash America Pawn",
  "slug": "cash-america-pawn-brandon",
  "category": "pawn-shops",
  "subcategories": [],
  "description_short": "Cash America Pawn at 115 E Brandon Blvd, Brandon, FL 33511 is Mon-Fri 9:00\u202fAM\u2009\u2013\u20096:00\u202fPM. Google reviewers rate the branch 4.5 stars across 196 reviews. Call +1 813-643-0771.",
  "description_long": "Cash America Pawn is now part of FirstCash Holdings, Inc., formed after FirstCash acquired Cash America International in 2016. Headquartered at 1600 West 7th Street in Fort Worth, Texas, FirstCash is publicly traded and included in the S&P MidCap 400 Index and Russell 2000 Index. With approximately 22,000 employees, it is the largest international operator of pawn stores in the world, with a presence in 29 U.S. states and the District of Columbia, the United Kingdom, and across Latin America \u2014 including all Mexican states and the countries of Guatemala, Colombia, and El Salvador.\n\nFirstCash offers two core services under the Cash America Pawn banner: pawn loans and retail sales. Pawn loans are small, non-recourse loans secured by pledged personal property \u2014 meaning the borrower owes nothing beyond the collateral if they choose not to repay. The company buys and accepts as collateral a wide range of merchandise including jewelry, electronics, tools, appliances, sporting goods, musical instruments, and more. In addition to pawn lending, it operates as a retail resale marketplace where customers can purchase pre-owned goods at discounted prices. FirstCash also buys gold, silver, and platinum outright for immediate cash. A layaway program allows customers to hold items with a 10% down payment.\n\nWhat distinguishes FirstCash from independent pawnbrokers is its scale and institutional backing. Operating over 3,300 locations, it offers standardized processes and a store locator for ease of access. Through its wholly owned subsidiary American First Finance (AFF), FirstCash also provides lease-to-own and retail finance payment solutions through a network of more than 15,000 active merchant partner locations \u2014 extending its reach well beyond traditional pawn into broader consumer credit services for underbanked populations.\n\nFor consumers in genuine financial distress who own items of value, Cash America Pawn locations provide fast, no-credit-check access to cash. However, pawn loans typically carry high implicit interest rates and short repayment windows, and the website provides no APR disclosures or specific loan terms. Borrowers who cannot repay will permanently lose their pledged item. This is a last-resort liquidity tool, not a cost-effective credit product. Best used for small, short-term needs when faster or cheaper alternatives have been exhausted.",
  "logo_url": "/logos/cash-america-pawn-brandon.png",
  "website_url": "https://www.firstcash.com",
  "affiliate_url": "",
  "affiliate_program": "",
  "phone": "+1 813-643-0771",
  "address": "115 E Brandon Blvd, Brandon, FL 33511",
  "pricing": {
    "monthly_price": 0,
    "setup_fee": 0,
    "money_back_guarantee": false,
    "guarantee_details": "",
    "free_consultation": true,
    "tiers": [],
    "currency": "USD"
  },
  "features": {
    "credit_monitoring": false,
    "all_three_bureaus": false,
    "goodwill_letters": false,
    "cease_desist_letters": false,
    "debt_validation": false,
    "credit_education": false,
    "identity_theft_protection": false,
    "score_tracking": false,
    "mobile_app": false,
    "online_portal": false,
    "personal_advisor": false,
    "ai_powered": false
  },
  "company_info": {
    "founded_year": 0,
    "headquarters": "115 E Brandon Blvd, Brandon, FL 33511",
    "city": "Brandon",
    "state": "Florida",
    "employees": "",
    "bbb_rating": "NR",
    "bbb_accredited": false,
    "certifications": []
  },
  "states_served": [
    "Florida"
  ],
  "cities_served": [
    "Brandon"
  ],
  "rating": 3.9,
  "rating_breakdown": {
    "value": 5.0,
    "effectiveness": 3.5,
    "customer_service": 3.7,
    "transparency": 3.5,
    "ease_of_use": 3.9
  },
  "pros": [
    "3,300+ locations across 29 U.S. states, UK, and Latin America \u2014 highly accessible",
    "Non-recourse pawn loans: if you can't repay, you owe nothing beyond the forfeited item",
    "No credit check required \u2014 approval based solely on item value",
    "Buys a wide range of items: jewelry, electronics, tools, appliances, sporting goods, musical instruments",
    "Immediate cash for gold, silver, and platinum purchases",
    "Layaway program available with only 10% down on purchases",
    "Publicly traded, institutionally governed company (S&P MidCap 400) \u2014 more accountability than independent shops"
  ],
  "cons": [
    "No APR or loan fee disclosures on the website \u2014 borrowers must visit in-store to learn actual cost",
    "Pawn loans are inherently high-cost compared to personal loans or credit cards",
    "Losing the pledged item is a real risk \u2014 common for borrowers in ongoing financial distress",
    "Cash America brand has been consolidated into FirstCash \u2014 store branding and policies may vary by location",
    "Loan amounts are small and tied to assessed item value, which stores typically set conservatively"
  ],
  "best_for": [
    "Unbanked or credit-invisible consumers who need fast cash without a credit check",
    "People with jewelry, electronics, or valuables they want to sell outright for immediate cash",
    "Budget shoppers seeking discounted secondhand merchandise",
    "Consumers who need a short-term bridge loan and own an item they are willing to risk as collateral"
  ],
  "similar_lenders": [],
  "diagnosis": "Cash America Pawn (now FirstCash) is best for cash-strapped consumers who own items of value and need money immediately without a credit check \u2014 no application, no approval process, just collateral. The main caveat is cost opacity: the website lists no rates or fees, and pawn loans are among the most expensive short-term credit products available, making them appropriate only when faster or cheaper alternatives are unavailable.",
  "services": [
    "Pawn loans (non-recourse, secured by personal property)",
    "Outright purchase of jewelry, electronics, tools, appliances, sporting goods, and musical instruments",
    "Gold, silver, and platinum buying for immediate cash",
    "Retail sales of pre-owned merchandise",
    "Layaway program (10% down payment)",
    "Store locator across 3,300+ U.S. and international locations",
    "Lease-to-own payment solutions (through AFF subsidiary)",
    "Retail finance solutions for consumer goods and services (through AFF, 15,000+ merchant locations)"
  ],
  "typical_results_timeline": "",
  "last_updated": "2026-03-21",
  "review_status": "published",
  "data_source": "enriched",
  "google_data": {
    "google_id": "0x88c2cdcbfb3c6eb3:0x5e8e701a0299b3ea",
    "google_rating": 4.5,
    "google_reviews_count": 185,
    "latitude": 27.9374985,
    "longitude": -82.284854,
    "phone": "+1 813-643-0771",
    "working_hours": {
      "Friday": [
        "9AM-6PM"
      ],
      "Monday": [
        "9AM-6PM"
      ],
      "Saturday": [
        "9AM-6PM"
      ],
      "Sunday": [
        "12-5PM"
      ],
      "Thursday": [
        "9AM-6PM"
      ],
      "Tuesday": [
        "9AM-6PM"
      ],
      "Wednesday": [
        "9AM-6PM"
      ]
    }
  },
  "website": "https://www.firstcash.com",
  "processing_status": "ready_for_index",
  "quality_score": 10,
  "enrichment_attempts": 1,
  "last_engine_run": "2026-03-26",
  "has_been_enriched": true,
  "contact": {
    "phone": "",
    "address": ""
  },
  "brand_slug": "cash-america-pawn"
}