{
  "name": "Cash1",
  "slug": "cash1-sacramento-ca",
  "category": "fix-my-credit",
  "subcategories": [],
  "description_short": "Cash1 — Financial institution in Sacramento, CA.",
  "description_long": "Cash1 provides Financial institution. Located at 1600 W El Camino Ave, Sacramento, CA 95833.",
  "logo_url": "https://lh6.googleusercontent.com/-txy-_iyqZ1I/AAAAAAAAAAI/AAAAAAAAAAA/NoiSMXWEg2c/s44-p-k-no-ns-nd/photo.jpg",
  "website_url": "https://cash1.ccfi.com/",
  "affiliate_url": "",
  "affiliate_program": "",
  "phone": "+1 916-643-2274",
  "address": "1600 W El Camino Ave, Sacramento, CA 95833",
  "pricing": {
    "monthly_price": 0,
    "setup_fee": 0,
    "money_back_guarantee": false,
    "guarantee_details": "",
    "free_consultation": true,
    "tiers": [],
    "currency": "USD"
  },
  "features": {
    "credit_monitoring": false,
    "all_three_bureaus": false,
    "goodwill_letters": false,
    "cease_desist_letters": false,
    "debt_validation": false,
    "credit_education": false,
    "identity_theft_protection": false,
    "score_tracking": false,
    "mobile_app": false,
    "online_portal": false,
    "personal_advisor": false,
    "ai_powered": false
  },
  "company_info": {
    "founded_year": 0,
    "headquarters": "1600 W El Camino Ave, Sacramento, CA 95833",
    "city": "Sacramento",
    "state": "California",
    "employees": "",
    "bbb_rating": "NR",
    "bbb_accredited": false,
    "certifications": []
  },
  "states_served": [
    "California"
  ],
  "cities_served": [
    "Sacramento"
  ],
  "rating": 4.7,
  "rating_breakdown": {
    "value": 0,
    "effectiveness": 0,
    "customer_service": 4.7,
    "transparency": 0,
    "ease_of_use": 0
  },
  "pros": [],
  "cons": [],
  "best_for": [],
  "similar_lenders": [],
  "diagnosis": "",
  "services": [
    "Financial institution"
  ],
  "typical_results_timeline": "",
  "last_updated": "2026-03-31",
  "review_status": "published",
  "data_source": "outscraper",
  "google_data": {
    "google_id": "0x809ad6fb48102bfb:0x274c99612c3d9b6b",
    "google_rating": 4.7,
    "google_reviews_count": 466,
    "latitude": 38.61232,
    "longitude": -121.49835999999999,
    "phone": "+1 916-643-2274",
    "working_hours": {
      "Friday": [
        "9AM-7PM"
      ],
      "Monday": [
        "9AM-7PM"
      ],
      "Saturday": [
        "10AM-4PM"
      ],
      "Sunday": [
        "Closed"
      ],
      "Thursday": [
        "9AM-7PM"
      ],
      "Tuesday": [
        "9AM-7PM"
      ],
      "Wednesday": [
        "9AM-7PM"
      ]
    }
  },
  "processing_status": "raw",
  "quality_score": 1,
  "enrichment_attempts": 0,
  "last_engine_run": "2000-01-01",
  "website_needs_review": true
}