{
  "name": "Jefferson Law, LLC",
  "slug": "jefferson-law",
  "category": "fix-my-credit",
  "subcategories": [],
  "description_short": "Jefferson Law, LLC — Lawyer in Philadelphia, PA.",
  "description_long": "Jefferson Law, LLC provides Lawyer. Located at BNY Mellon Center, 1735 Market St #3750, Philadelphia, PA 19103.",
  "logo_url": "https://lh5.googleusercontent.com/-tl98o0JSgGI/AAAAAAAAAAI/AAAAAAAAAAA/x3gviiZliqY/s44-p-k-no-ns-nd/photo.jpg",
  "website_url": "https://hjeffersonlawfirm.com/",
  "affiliate_url": "",
  "affiliate_program": "",
  "phone": "+1 215-399-0911",
  "address": "BNY Mellon Center, 1735 Market St #3750, Philadelphia, PA 19103",
  "pricing": {
    "monthly_price": 0,
    "setup_fee": 0,
    "money_back_guarantee": false,
    "guarantee_details": "",
    "free_consultation": true,
    "tiers": [],
    "currency": "USD"
  },
  "features": {
    "credit_monitoring": false,
    "all_three_bureaus": false,
    "goodwill_letters": false,
    "cease_desist_letters": false,
    "debt_validation": false,
    "credit_education": false,
    "identity_theft_protection": false,
    "score_tracking": false,
    "mobile_app": false,
    "online_portal": false,
    "personal_advisor": false,
    "ai_powered": false
  },
  "company_info": {
    "founded_year": 0,
    "headquarters": "BNY Mellon Center, 1735 Market St #3750, Philadelphia, PA 19103",
    "city": "Philadelphia",
    "state": "Pennsylvania",
    "employees": "",
    "bbb_rating": "NR",
    "bbb_accredited": false,
    "certifications": []
  },
  "states_served": [
    "Pennsylvania"
  ],
  "cities_served": [
    "Philadelphia"
  ],
  "rating": 3.0,
  "rating_breakdown": {
    "value": 0,
    "effectiveness": 0,
    "customer_service": 3.0,
    "transparency": 0,
    "ease_of_use": 0
  },
  "pros": [],
  "cons": [],
  "best_for": [],
  "similar_lenders": [],
  "diagnosis": "",
  "services": [
    "Lawyer"
  ],
  "typical_results_timeline": "",
  "last_updated": "2026-04-02",
  "review_status": "published",
  "data_source": "outscraper",
  "google_data": {
    "google_id": "0x89c6c78b9de01e65:0xb1e60e9c6800f23e",
    "google_rating": 3.0,
    "google_reviews_count": 2,
    "latitude": 39.9536631,
    "longitude": -75.1695865,
    "phone": "+1 215-399-0911",
    "working_hours": {
      "Friday": [
        "8:30AM-5:30PM"
      ],
      "Monday": [
        "8:30AM-5:30PM"
      ],
      "Saturday": [
        "Closed"
      ],
      "Sunday": [
        "Closed"
      ],
      "Thursday": [
        "8:30AM-5:30PM"
      ],
      "Tuesday": [
        "8:30AM-5:30PM"
      ],
      "Wednesday": [
        "8:30AM-5:30PM"
      ]
    }
  },
  "processing_status": "raw",
  "quality_score": 1,
  "enrichment_attempts": 0,
  "last_engine_run": "2026-03-31",
  "no_index": true,
  "website_needs_review": true,
  "contact": {
    "phone": "",
    "address": ""
  }
}
