{
  "name": "Northwest Community Credit Union",
  "slug": "northwest-community-credit-union",
  "category": "payday-alternatives",
  "subcategories": [],
  "description_short": "Northwest Community Credit Union — Credit union in Morton Grove, IL.",
  "description_long": "Northwest Community Credit Union provides Credit union. Located at 8930 N Waukegan Rd, Morton Grove, IL 60053.",
  "logo_url": "https://lh6.googleusercontent.com/-Q2a4BQNJMr8/AAAAAAAAAAI/AAAAAAAAAAA/nK_AmBC71W4/s44-p-k-no-ns-nd/photo.jpg",
  "website_url": "https://www.nwccu.com/",
  "affiliate_url": "",
  "affiliate_program": "",
  "phone": "+1 847-647-1030",
  "address": "8930 N Waukegan Rd, Morton Grove, IL 60053",
  "pricing": {
    "monthly_price": 0,
    "setup_fee": 0,
    "money_back_guarantee": false,
    "guarantee_details": "",
    "free_consultation": true,
    "tiers": [],
    "currency": "USD"
  },
  "features": {
    "credit_monitoring": false,
    "all_three_bureaus": false,
    "goodwill_letters": false,
    "cease_desist_letters": false,
    "debt_validation": false,
    "credit_education": false,
    "identity_theft_protection": false,
    "score_tracking": false,
    "mobile_app": false,
    "online_portal": false,
    "personal_advisor": false,
    "ai_powered": false
  },
  "company_info": {
    "founded_year": 0,
    "headquarters": "8930 N Waukegan Rd, Morton Grove, IL 60053",
    "city": "Morton Grove",
    "state": "Illinois",
    "employees": "",
    "bbb_rating": "NR",
    "bbb_accredited": false,
    "certifications": []
  },
  "states_served": [
    "Illinois"
  ],
  "cities_served": [
    "Morton Grove"
  ],
  "rating": 4.8,
  "rating_breakdown": {
    "value": 0,
    "effectiveness": 0,
    "customer_service": 4.8,
    "transparency": 0,
    "ease_of_use": 0
  },
  "pros": [],
  "cons": [],
  "best_for": [],
  "similar_lenders": [],
  "diagnosis": "",
  "services": [
    "Credit union"
  ],
  "typical_results_timeline": "",
  "last_updated": "2026-04-01",
  "review_status": "published",
  "data_source": "outscraper",
  "google_data": {
    "google_id": "0x880fc8969a42bfc1:0x6ec016e27053261f",
    "google_rating": 4.8,
    "google_reviews_count": 23,
    "latitude": 42.0435867,
    "longitude": -87.7996507,
    "phone": "+1 847-647-1030",
    "working_hours": {
      "Friday": [
        "9AM-6PM"
      ],
      "Monday": [
        "8AM-5PM"
      ],
      "Saturday": [
        "Closed"
      ],
      "Sunday": [
        "Closed"
      ],
      "Thursday": [
        "8AM-5PM"
      ],
      "Tuesday": [
        "8AM-5PM"
      ],
      "Wednesday": [
        "8AM-12PM"
      ]
    }
  },
  "processing_status": "raw",
  "quality_score": 1,
  "enrichment_attempts": 0,
  "last_engine_run": "2026-03-31",
  "website_needs_review": true,
  "no_index": true
}