{
  "name": "Prunto Motor Inc.",
  "slug": "prunto-motor",
  "category": "personal-loans",
  "subcategories": [],
  "description_short": "Prunto Motor Inc. \u2014 Used car dealer in Dearborn, MI.",
  "description_long": "Prunto Motor Inc. provides Used car dealer. Located at 7750 Greenfield Rd SUITE 101, Dearborn, MI 48126.",
  "logo_url": "https://lh5.googleusercontent.com/-UIymLqYI-D4/AAAAAAAAAAI/AAAAAAAAAAA/Y5gPGb_YdRE/s44-p-k-no-ns-nd/photo.jpg",
  "website_url": "",
  "affiliate_url": "",
  "affiliate_program": "",
  "phone": "+1 313-724-6430",
  "address": "7750 Greenfield Rd SUITE 101, Dearborn, MI 48126",
  "pricing": {
    "monthly_price": 0,
    "setup_fee": 0,
    "money_back_guarantee": false,
    "guarantee_details": "",
    "free_consultation": true,
    "tiers": [],
    "currency": "USD"
  },
  "features": {
    "credit_monitoring": false,
    "all_three_bureaus": false,
    "goodwill_letters": false,
    "cease_desist_letters": false,
    "debt_validation": false,
    "credit_education": false,
    "identity_theft_protection": false,
    "score_tracking": false,
    "mobile_app": false,
    "online_portal": false,
    "personal_advisor": false,
    "ai_powered": false
  },
  "company_info": {
    "founded_year": 0,
    "headquarters": "7750 Greenfield Rd SUITE 101, Dearborn, MI 48126",
    "city": "Dearborn",
    "state": "Michigan",
    "employees": "",
    "bbb_rating": "NR",
    "bbb_accredited": false,
    "certifications": []
  },
  "states_served": [
    "Michigan"
  ],
  "cities_served": [
    "Dearborn"
  ],
  "rating": 3.3,
  "rating_breakdown": {
    "value": 0,
    "effectiveness": 0,
    "customer_service": 3.3,
    "transparency": 0,
    "ease_of_use": 0
  },
  "pros": [],
  "cons": [],
  "best_for": [],
  "similar_lenders": [],
  "diagnosis": "",
  "services": [
    "Used car dealer"
  ],
  "typical_results_timeline": "",
  "last_updated": "2026-03-21",
  "review_status": "published",
  "data_source": "outscraper",
  "google_data": {
    "google_id": "0x883b34cd5b682e9d:0x585f6b8bdebe48d8",
    "google_rating": 3.3,
    "google_reviews_count": 58,
    "latitude": 42.348722099999996,
    "longitude": -83.19593239999999,
    "phone": "+1 313-724-6430",
    "working_hours": {
      "Friday": [
        "10AM-5PM"
      ],
      "Monday": [
        "10AM-5PM"
      ],
      "Saturday": [
        "10AM-4PM"
      ],
      "Sunday": [
        "Closed"
      ],
      "Thursday": [
        "10AM-5PM"
      ],
      "Tuesday": [
        "10AM-5PM"
      ],
      "Wednesday": [
        "10AM-5PM"
      ]
    }
  },
  "processing_status": "raw",
  "quality_score": 1,
  "enrichment_attempts": 0,
  "last_engine_run": null
}