{
  "name": "S&L Jewelers",
  "slug": "sl-jewelers",
  "category": "fix-my-credit",
  "subcategories": [],
  "description_short": "S&L Jewelers \u2014 Jeweler in Memphis, TN.",
  "description_long": "S&L Jewelers provides Jeweler. Located at 7166 Winchester Rd #105, Memphis, TN 38125.",
  "logo_url": "https://lh3.googleusercontent.com/-EuWoSVPoPmI/AAAAAAAAAAI/AAAAAAAAAAA/ylEUhotnKw0/s44-p-k-no-ns-nd/photo.jpg",
  "website_url": "",
  "affiliate_url": "",
  "affiliate_program": "",
  "phone": "+1 901-600-4894",
  "address": "7166 Winchester Rd #105, Memphis, TN 38125",
  "pricing": {
    "monthly_price": 0,
    "setup_fee": 0,
    "money_back_guarantee": false,
    "guarantee_details": "",
    "free_consultation": true,
    "tiers": [],
    "currency": "USD"
  },
  "features": {
    "credit_monitoring": false,
    "all_three_bureaus": false,
    "goodwill_letters": false,
    "cease_desist_letters": false,
    "debt_validation": false,
    "credit_education": false,
    "identity_theft_protection": false,
    "score_tracking": false,
    "mobile_app": false,
    "online_portal": false,
    "personal_advisor": false,
    "ai_powered": false
  },
  "company_info": {
    "founded_year": 0,
    "headquarters": "7166 Winchester Rd #105, Memphis, TN 38125",
    "city": "Memphis",
    "state": "Tennessee",
    "employees": "",
    "bbb_rating": "NR",
    "bbb_accredited": false,
    "certifications": []
  },
  "states_served": [
    "Tennessee"
  ],
  "cities_served": [
    "Memphis"
  ],
  "rating": 4.7,
  "rating_breakdown": {
    "value": 0,
    "effectiveness": 0,
    "customer_service": 4.7,
    "transparency": 0,
    "ease_of_use": 0
  },
  "pros": [],
  "cons": [],
  "best_for": [],
  "similar_lenders": [],
  "diagnosis": "",
  "services": [
    "Jeweler"
  ],
  "typical_results_timeline": "",
  "last_updated": "2026-03-21",
  "review_status": "published",
  "data_source": "outscraper",
  "google_data": {
    "google_id": "0x887f9bd751e2dfb7:0xdeca3d79897fef16",
    "google_rating": 4.7,
    "google_reviews_count": 13,
    "latitude": 35.0494649,
    "longitude": -89.82382609999999,
    "phone": "+1 901-600-4894",
    "working_hours": {
      "Friday": [
        "11AM-7PM"
      ],
      "Monday": [
        "11AM-7PM"
      ],
      "Saturday": [
        "11AM-7PM"
      ],
      "Sunday": [
        "12-5PM"
      ],
      "Thursday": [
        "11AM-7PM"
      ],
      "Tuesday": [
        "11AM-7PM"
      ],
      "Wednesday": [
        "11AM-7PM"
      ]
    }
  }
}