{
  "name": "Star Credit Repair",
  "slug": "star-credit-repair-miami",
  "category": "fix-my-credit",
  "subcategories": [],
  "description_short": "Star Credit Repair \u2014 Credit counseling service in Miami, FL.",
  "description_long": "Star Credit Repair provides Credit counseling service. Located at 1001 Brickell Bay Dr, Miami, FL 33131.",
  "logo_url": "https://lh6.googleusercontent.com/-B8izIGs0qfA/AAAAAAAAAAI/AAAAAAAAAAA/Kk3CDpDjRyI/s44-p-k-no-ns-nd/photo.jpg",
  "website_url": "",
  "affiliate_url": "",
  "affiliate_program": "",
  "phone": "+1 786-568-7794",
  "address": "1001 Brickell Bay Dr, Miami, FL 33131",
  "pricing": {
    "monthly_price": 0,
    "setup_fee": 0,
    "money_back_guarantee": false,
    "guarantee_details": "",
    "free_consultation": true,
    "tiers": [],
    "currency": "USD"
  },
  "features": {
    "credit_monitoring": false,
    "all_three_bureaus": false,
    "goodwill_letters": false,
    "cease_desist_letters": false,
    "debt_validation": false,
    "credit_education": false,
    "identity_theft_protection": false,
    "score_tracking": false,
    "mobile_app": false,
    "online_portal": false,
    "personal_advisor": false,
    "ai_powered": false
  },
  "company_info": {
    "founded_year": 0,
    "headquarters": "1001 Brickell Bay Dr, Miami, FL 33131",
    "city": "Miami",
    "state": "Florida",
    "employees": "",
    "bbb_rating": "NR",
    "bbb_accredited": false,
    "certifications": []
  },
  "states_served": [
    "Florida"
  ],
  "cities_served": [
    "Miami"
  ],
  "rating": 0,
  "rating_breakdown": {
    "value": 0,
    "effectiveness": 0,
    "customer_service": 0,
    "transparency": 0,
    "ease_of_use": 0
  },
  "pros": [],
  "cons": [],
  "best_for": [],
  "similar_lenders": [],
  "diagnosis": "",
  "services": [
    "Credit counseling service"
  ],
  "typical_results_timeline": "",
  "last_updated": "2026-03-21",
  "review_status": "published",
  "data_source": "outscraper",
  "google_data": {
    "google_id": "0x88d9b76a66e64f73:0x3d2d81867a335e11",
    "google_rating": null,
    "google_reviews_count": 0,
    "latitude": 25.7636109,
    "longitude": -80.1891193,
    "phone": "+1 786-568-7794",
    "working_hours": {
      "Friday": [
        "8AM-6PM"
      ],
      "Monday": [
        "8AM-6PM"
      ],
      "Saturday": [
        "8AM-6PM"
      ],
      "Sunday": [
        "8AM-6PM"
      ],
      "Thursday": [
        "8AM-6PM"
      ],
      "Tuesday": [
        "8AM-6PM"
      ],
      "Wednesday": [
        "8AM-6PM"
      ]
    }
  },
  "processing_status": "raw",
  "quality_score": 0,
  "enrichment_attempts": 0,
  "last_engine_run": null
}