{
  "name": "Stevens Creek Subaru",
  "slug": "stevens-creek-subaru",
  "category": "fix-my-credit",
  "subcategories": [],
  "description_short": "Stevens Creek Subaru \u2014 Subaru dealer in San Jose, CA.",
  "description_long": "Stevens Creek Subaru provides Subaru dealer. Located at 3225 Stevens Creek Blvd, San Jose, CA 95117.",
  "logo_url": "https://lh4.googleusercontent.com/-6Z1uBRfHmQo/AAAAAAAAAAI/AAAAAAAAAAA/2F2aBXC7AkQ/s44-p-k-no-ns-nd/photo.jpg",
  "website_url": "https://www.stevenscreeksubaru.com/?srsltid=AfmBOoq7rupOnSWZrrSuM5GoANrKy_n0zeHnduHxcrUv6ymYljVqMevh",
  "affiliate_url": "",
  "affiliate_program": "",
  "phone": "+1 408-984-2001",
  "address": "3225 Stevens Creek Blvd, San Jose, CA 95117",
  "pricing": {
    "monthly_price": 0,
    "setup_fee": 0,
    "money_back_guarantee": false,
    "guarantee_details": "",
    "free_consultation": true,
    "tiers": [],
    "currency": "USD"
  },
  "features": {
    "credit_monitoring": false,
    "all_three_bureaus": false,
    "goodwill_letters": false,
    "cease_desist_letters": false,
    "debt_validation": false,
    "credit_education": false,
    "identity_theft_protection": false,
    "score_tracking": false,
    "mobile_app": false,
    "online_portal": false,
    "personal_advisor": false,
    "ai_powered": false
  },
  "company_info": {
    "founded_year": 0,
    "headquarters": "3225 Stevens Creek Blvd, San Jose, CA 95117",
    "city": "San Jose",
    "state": "California",
    "employees": "",
    "bbb_rating": "NR",
    "bbb_accredited": false,
    "certifications": []
  },
  "states_served": [
    "California"
  ],
  "cities_served": [
    "San Jose"
  ],
  "rating": 4.3,
  "rating_breakdown": {
    "value": 0,
    "effectiveness": 0,
    "customer_service": 4.3,
    "transparency": 0,
    "ease_of_use": 0
  },
  "pros": [],
  "cons": [],
  "best_for": [],
  "similar_lenders": [],
  "diagnosis": "",
  "services": [
    "Subaru dealer"
  ],
  "typical_results_timeline": "",
  "last_updated": "2026-03-23",
  "review_status": "published",
  "data_source": "outscraper",
  "google_data": {
    "google_id": "0x808fcae131970085:0x2830ab4a74e22c3b",
    "google_rating": 4.3,
    "google_reviews_count": 2107,
    "latitude": 37.3235782,
    "longitude": -121.95376569999999,
    "phone": "+1 408-984-2001",
    "working_hours": {
      "Friday": [
        "9AM-8PM"
      ],
      "Monday": [
        "9AM-8PM"
      ],
      "Saturday": [
        "9AM-8PM"
      ],
      "Sunday": [
        "10AM-8PM"
      ],
      "Thursday": [
        "9AM-8PM"
      ],
      "Tuesday": [
        "9AM-8PM"
      ],
      "Wednesday": [
        "9AM-8PM"
      ]
    }
  },
  "processing_status": "raw",
  "quality_score": 2,
  "enrichment_attempts": 0,
  "last_engine_run": null
}