{
  "name": "Western Union",
  "slug": "western-union-milwaukee-wi",
  "category": "emergency-cash",
  "subcategories": [],
  "description_short": "Western Union \u2014 Money transfer service in Milwaukee, WI.",
  "description_long": "Western Union provides Money transfer service. Located at 5200 W Oklahoma Ave, Milwaukee, WI 53219.",
  "logo_url": "https://lh5.googleusercontent.com/-t4R7KRqHdRY/AAAAAAAAAAI/AAAAAAAAAAA/JPGrKHhHm9s/s44-p-k-no-ns-nd/photo.jpg",
  "website_url": "",
  "affiliate_url": "",
  "affiliate_program": "",
  "phone": "+1 414-541-5200",
  "address": "5200 W Oklahoma Ave, Milwaukee, WI 53219",
  "pricing": {
    "monthly_price": 0,
    "setup_fee": 0,
    "money_back_guarantee": false,
    "guarantee_details": "",
    "free_consultation": true,
    "tiers": [],
    "currency": "USD"
  },
  "features": {
    "credit_monitoring": false,
    "all_three_bureaus": false,
    "goodwill_letters": false,
    "cease_desist_letters": false,
    "debt_validation": false,
    "credit_education": false,
    "identity_theft_protection": false,
    "score_tracking": false,
    "mobile_app": false,
    "online_portal": false,
    "personal_advisor": false,
    "ai_powered": false
  },
  "company_info": {
    "founded_year": 0,
    "headquarters": "5200 W Oklahoma Ave, Milwaukee, WI 53219",
    "city": "Milwaukee",
    "state": "Wisconsin",
    "employees": "",
    "bbb_rating": "NR",
    "bbb_accredited": false,
    "certifications": []
  },
  "states_served": [
    "Wisconsin"
  ],
  "cities_served": [
    "Milwaukee"
  ],
  "rating": 2.1,
  "rating_breakdown": {
    "value": 2.0,
    "effectiveness": 1.0,
    "customer_service": 2.2,
    "transparency": 2.0,
    "ease_of_use": 3.7
  },
  "pros": [],
  "cons": [],
  "best_for": [],
  "similar_lenders": [],
  "diagnosis": "",
  "services": [
    "Money transfer service"
  ],
  "typical_results_timeline": "",
  "last_updated": "2026-03-21",
  "review_status": "published",
  "data_source": "outscraper",
  "google_data": {
    "google_id": "0x88051064452f8345:0x8b1c3115c061d06f",
    "google_rating": 5.0,
    "google_reviews_count": 1,
    "latitude": 42.988733499999995,
    "longitude": -87.9794259,
    "phone": "+1 414-541-5200",
    "working_hours": {
      "Friday": [
        "6:30AM-11PM"
      ],
      "Monday": [
        "6:30AM-11PM"
      ],
      "Saturday": [
        "6:30AM-10:30PM"
      ],
      "Sunday": [
        "6:30AM-10:30PM"
      ],
      "Thursday": [
        "6:30AM-11PM"
      ],
      "Tuesday": [
        "6:30AM-11PM"
      ],
      "Wednesday": [
        "6:30AM-11PM"
      ]
    }
  },
  "processing_status": "raw",
  "quality_score": 0,
  "enrichment_attempts": 0,
  "last_engine_run": "2026-03-31",
  "no_index": true,
  "contact": {
    "phone": "",
    "address": ""
  }
}